minuteinbox/__init__.py
minuteinbox/api.py
minuteinbox/classes.py
minuteinbox-0.3.0.dist-info/LICENSE
minuteinbox-0.3.0.dist-info/WHEEL
minuteinbox-0.3.0.dist-info/METADATA
minuteinbox-0.3.0.dist-info/RECORD
